{
  "uuid": "f625fb75-5f98-45da-8e19-4059bc80dbf6",
  "set": "Discover and Learn",
  "type": "Homework",
  "title": "Tour of PrairieLearn",
  "number": "1",
  "allowAccess": [
    {
      "startDate": "2023-01-17T00:00:01",
      "credit": 100
    }
  ],
  "text": "This assessment walks you through the various types of questions that you may encounter on PrairieLearn.",
  "zones": [
    {
      "title": "Question types",
      "questions": [
        { "id": "tour/choices", "points": 1 },
        { "id": "tour/open", "points": 1 },
        { "id": "tour/numeric", "points": 1 },
        { "id": "tour/text", "points": 1 },
        { "id": "tour/order_blocks", "points": 1 },
          { "id": "demos/checkbox_feedback", "points": 1 },
          { "id": "demos/hints", "points": 1 },
          { "id": "demos/hiddenHints", "points": 1 },
          { "id": "demos/prose", "points": 1 },
          { "id": "demos/manual", "points": 1 },
          { "id": "demos/gradeFunction", "points": 1 },
        { "id": "tour/upload", "points": 1 },
        { "id": "tour/drawing", "points": 1 }      ]
    }
  ]
}
